{
  "dashboardBindSet": [],
  "dashboardExtend": {
    "groupUnfoldStatus": {
      "{{.Dashboard.category_bufferpool}}": true,
      "{{.Dashboard.category_connections}}": true,
      "{{.Dashboard.category_database}}": true,
      "{{.Dashboard.category_locks}}": true,
      "{{.Dashboard.category_log}}": true,
      "{{.Dashboard.category_overview}}": true,
      "{{.Dashboard.category_readwrite}}": true,
      "{{.Dashboard.category_tablespace}}": true
    }
  },
  "dashboardMapping": [],
  "dashboardOwnerType": "node",
  "dashboardType": "CUSTOM",
  "iconSet": {},
  "main": {
    "charts": [
      {
        "extend": {
          "fixedTime": "",
          "isRefresh": false,
          "settings": {
            "alias": [],
            "chartType": "areaLine",
            "colors": [],
            "compareColors": {
              "dayCompare": "rgba(213,217,226,0.5)",
              "hourCompare": "#D5D9E2",
              "monthCompare": "rgba(213,217,226,0.12)",
              "weekCompare": "rgba(213,217,226,0.25)"
            },
            "compareColorsDark": {
              "dayCompare": "rgba(213,217,226,0.5)",
              "hourCompare": "#D5D9E2",
              "monthCompare": "rgba(213,217,226,0.12)",
              "weekCompare": "rgba(213,217,226,0.25)"
            },
            "compareColorsLight": {
              "dayCompare": "rgba(11,11,12,0.5)",
              "hourCompare": "#0B0B0C",
              "monthCompare": "rgba(11,11,12,0.12)",
              "weekCompare": "rgba(11,11,12,0.3)"
            },
            "compareType": [],
            "currentChartType": "sequence",
            "density": "medium",
            "fixedTime": "",
            "isPercent": false,
            "isTimeInterval": true,
            "legendPostion": "none",
            "legendValues": "",
            "levels": [],
            "mainMeasurementQueryCode": "A",
            "onlyShowGroupName": false,
            "openCompare": false,
            "openStack": false,
            "showFieldMapping": false,
            "showLine": false,
            "showTitle": true,
            "slimit": 20,
            "stackType": "time",
            "timeInterval": "auto",
            "titleDesc": "",
            "units": [],
            "xAxisShowType": "time",
            "yAxixMaxVal": null,
            "yAxixMinVal": null
          }
        },
        "group": {
          "name": "{{.Dashboard.category_connections}}"
        },
        "name": "{{.Dashboard.connection_active}}",
        "pos": {
          "h": 9,
          "w": 6,
          "x": 0,
          "y": 0
        },
        "queries": [
          {
            "color": "",
            "datasource": "dataflux",
            "name": "",
            "qtype": "dql",
            "query": {
              "alias": "",
              "code": "A",
              "dataSource": "db2_instance",
              "field": "connection_active",
              "fieldFunc": "last",
              "fieldType": "float",
              "fill": null,
              "filters": [],
              "funcList": [],
              "groupBy": [
                "db2_server"
              ],
              "groupByTime": "",
              "indexFilter": "",
              "namespace": "metric",
              "q": "M::`db2_instance`:(LAST(`connection_active`)) BY `db2_server`",
              "queryFuncs": [],
              "type": "simple"
            },
            "type": "sequence",
            "unit": ""
          }
        ],
        "type": "sequence"
      },
      {
        "extend": {
          "fixedTime": "",
          "isRefresh": false,
          "settings": {
            "alias": [],
            "chartType": "bar",
            "colors": [],
            "compareColors": {
              "dayCompare": "rgba(213,217,226,0.5)",
              "hourCompare": "#D5D9E2",
              "monthCompare": "rgba(213,217,226,0.12)",
              "weekCompare": "rgba(213,217,226,0.25)"
            },
            "compareColorsDark": {
              "dayCompare": "rgba(213,217,226,0.5)",
              "hourCompare": "#D5D9E2",
              "monthCompare": "rgba(213,217,226,0.12)",
              "weekCompare": "rgba(213,217,226,0.25)"
            },
            "compareColorsLight": {
              "dayCompare": "rgba(11,11,12,0.5)",
              "hourCompare": "#0B0B0C",
              "monthCompare": "rgba(11,11,12,0.12)",
              "weekCompare": "rgba(11,11,12,0.3)"
            },
            "compareType": [],
            "currentChartType": "sequence",
            "density": "medium",
            "fixedTime": "",
            "isPercent": false,
            "isTimeInterval": true,
            "legendPostion": "none",
            "legendValues": "",
            "levels": [],
            "mainMeasurementQueryCode": "A",
            "onlyShowGroupName": false,
            "openCompare": false,
            "openStack": false,
            "showFieldMapping": false,
            "showLine": false,
            "showTitle": true,
            "slimit": 20,
            "stackType": "time",
            "timeInterval": "auto",
            "titleDesc": "",
            "units": [],
            "xAxisShowType": "time",
            "yAxixMaxVal": null,
            "yAxixMinVal": null
          }
        },
        "group": {
          "name": "{{.Dashboard.category_connections}}"
        },
        "name": "{{.Dashboard.application_active}}",
        "pos": {
          "h": 9,
          "w": 6,
          "x": 6,
          "y": 0
        },
        "queries": [
          {
            "color": "",
            "datasource": "dataflux",
            "name": "",
            "qtype": "dql",
            "query": {
              "alias": "",
              "code": "A",
              "dataSource": "db2_database",
              "field": "application_active",
              "fieldFunc": "last",
              "fieldType": "float",
              "fill": null,
              "filters": [],
              "funcList": [],
              "groupBy": [
                "db2_server"
              ],
              "groupByTime": "",
              "indexFilter": "",
              "namespace": "metric",
              "q": "M::`db2_database`:(LAST(`application_active`)) BY `db2_server`",
              "queryFuncs": [],
              "type": "simple"
            },
            "type": "sequence",
            "unit": ""
          }
        ],
        "type": "sequence"
      },
      {
        "extend": {
          "fixedTime": "",
          "isRefresh": false,
          "settings": {
            "alias": [],
            "chartType": "line",
            "colors": [],
            "compareColors": {
              "dayCompare": "rgba(213,217,226,0.5)",
              "hourCompare": "#D5D9E2",
              "monthCompare": "rgba(213,217,226,0.12)",
              "weekCompare": "rgba(213,217,226,0.25)"
            },
            "compareColorsDark": {
              "dayCompare": "rgba(213,217,226,0.5)",
              "hourCompare": "#D5D9E2",
              "monthCompare": "rgba(213,217,226,0.12)",
              "weekCompare": "rgba(213,217,226,0.25)"
            },
            "compareColorsLight": {
              "dayCompare": "rgba(11,11,12,0.5)",
              "hourCompare": "#0B0B0C",
              "monthCompare": "rgba(11,11,12,0.12)",
              "weekCompare": "rgba(11,11,12,0.3)"
            },
            "compareType": [],
            "currentChartType": "sequence",
            "density": "medium",
            "fixedTime": "",
            "isPercent": false,
            "isTimeInterval": true,
            "legendPostion": "none",
            "legendValues": "",
            "levels": [],
            "mainMeasurementQueryCode": "A",
            "onlyShowGroupName": false,
            "openCompare": false,
            "openStack": false,
            "showFieldMapping": false,
            "showLine": false,
            "showTitle": true,
            "slimit": 20,
            "stackType": "time",
            "timeInterval": "auto",
            "titleDesc": "",
            "units": [
              {
                "key": "last(backup_latest)",
                "name": "last(backup_latest)",
                "unit": "",
                "units": [
                  "time",
                  "s"
                ]
              }
            ],
            "xAxisShowType": "time",
            "yAxixMaxVal": null,
            "yAxixMinVal": null
          }
        },
        "group": {
          "name": "{{.Dashboard.category_database}}"
        },
        "name": "{{.Dashboard.backup_latest}}",
        "pos": {
          "h": 11,
          "w": 8,
          "x": 8,
          "y": 0
        },
        "queries": [
          {
            "color": "",
            "datasource": "dataflux",
            "name": "",
            "qtype": "dql",
            "query": {
              "alias": "",
              "code": "A",
              "dataSource": "db2_database",
              "field": "backup_latest",
              "fieldFunc": "last",
              "fieldType": "float",
              "fill": null,
              "filters": [],
              "funcList": [],
              "groupBy": [
                "db2_server"
              ],
              "groupByTime": "",
              "indexFilter": "",
              "namespace": "metric",
              "q": "M::`db2_database`:(LAST(`backup_latest`)) BY `db2_server`",
              "queryFuncs": [],
              "type": "simple"
            },
            "type": "sequence",
            "unit": ""
          }
        ],
        "type": "sequence"
      },
      {
        "extend": {
          "fixedTime": "",
          "isRefresh": false,
          "settings": {
            "alias": [],
            "chartType": "line",
            "colors": [],
            "compareColors": {
              "dayCompare": "rgba(213,217,226,0.5)",
              "hourCompare": "#D5D9E2",
              "monthCompare": "rgba(213,217,226,0.12)",
              "weekCompare": "rgba(213,217,226,0.25)"
            },
            "compareColorsDark": {
              "dayCompare": "rgba(213,217,226,0.5)",
              "hourCompare": "#D5D9E2",
              "monthCompare": "rgba(213,217,226,0.12)",
              "weekCompare": "rgba(213,217,226,0.25)"
            },
            "compareColorsLight": {
              "dayCompare": "rgba(11,11,12,0.5)",
              "hourCompare": "#0B0B0C",
              "monthCompare": "rgba(11,11,12,0.12)",
              "weekCompare": "rgba(11,11,12,0.3)"
            },
            "compareType": [],
            "currentChartType": "sequence",
            "density": "medium",
            "fixedTime": "",
            "isPercent": false,
            "isTimeInterval": true,
            "legendPostion": "none",
            "legendValues": "",
            "levels": [],
            "mainMeasurementQueryCode": "A",
            "onlyShowGroupName": false,
            "openCompare": false,
            "openStack": false,
            "showFieldMapping": false,
            "showLine": false,
            "showTitle": true,
            "slimit": 20,
            "stackType": "time",
            "timeInterval": "auto",
            "titleDesc": "",
            "units": [],
            "xAxisShowType": "time",
            "yAxixMaxVal": null,
            "yAxixMinVal": null
          }
        },
        "group": {
          "name": "{{.Dashboard.category_locks}}"
        },
        "name": "{{.Dashboard.lock_dead}}",
        "pos": {
          "h": 10,
          "w": 12,
          "x": 0,
          "y": 0
        },
        "queries": [
          {
            "color": "",
            "datasource": "dataflux",
            "name": "",
            "qtype": "dql",
            "query": {
              "alias": "",
              "code": "A",
              "dataSource": "db2_database",
              "field": "lock_dead",
              "fieldFunc": "last",
              "fieldType": "float",
              "fill": null,
              "filters": [],
              "funcList": [],
              "groupBy": [
                "db2_server"
              ],
              "groupByTime": "",
              "indexFilter": "",
              "namespace": "metric",
              "q": "M::`db2_database`:(LAST(`lock_dead`)) BY `db2_server`",
              "queryFuncs": [],
              "type": "simple"
            },
            "type": "sequence",
            "unit": ""
          }
        ],
        "type": "sequence"
      },
      {
        "extend": {
          "fixedTime": "",
          "isRefresh": false,
          "settings": {
            "alias": [],
            "chartType": "line",
            "colors": [],
            "compareColors": {
              "dayCompare": "rgba(213,217,226,0.5)",
              "hourCompare": "#D5D9E2",
              "monthCompare": "rgba(213,217,226,0.12)",
              "weekCompare": "rgba(213,217,226,0.25)"
            },
            "compareColorsDark": {
              "dayCompare": "rgba(213,217,226,0.5)",
              "hourCompare": "#D5D9E2",
              "monthCompare": "rgba(213,217,226,0.12)",
              "weekCompare": "rgba(213,217,226,0.25)"
            },
            "compareColorsLight": {
              "dayCompare": "rgba(11,11,12,0.5)",
              "hourCompare": "#0B0B0C",
              "monthCompare": "rgba(11,11,12,0.12)",
              "weekCompare": "rgba(11,11,12,0.3)"
            },
            "compareType": [],
            "currentChartType": "sequence",
            "density": "medium",
            "fixedTime": "",
            "isPercent": false,
            "isTimeInterval": true,
            "legendPostion": "none",
            "legendValues": "",
            "levels": [],
            "mainMeasurementQueryCode": "A",
            "onlyShowGroupName": false,
            "openCompare": false,
            "openStack": false,
            "showFieldMapping": false,
            "showLine": false,
            "showTitle": true,
            "slimit": 20,
            "stackType": "time",
            "timeInterval": "auto",
            "titleDesc": "",
            "units": [],
            "xAxisShowType": "time",
            "yAxixMaxVal": null,
            "yAxixMinVal": null
          }
        },
        "group": {
          "name": "{{.Dashboard.category_readwrite}}"
        },
        "name": "{{.Dashboard.reads_returned_modified}}",
        "pos": {
          "h": 12,
          "w": 8,
          "x": 0,
          "y": 0
        },
        "queries": [
          {
            "color": "",
            "datasource": "dataflux",
            "name": "",
            "qtype": "dql",
            "query": {
              "alias": "",
              "code": "A",
              "dataSource": "db2_database",
              "field": "row_reads_total",
              "fieldFunc": "last",
              "fieldType": "float",
              "fill": null,
              "filters": [],
              "funcList": [],
              "groupBy": [
                "db2_server"
              ],
              "groupByTime": "",
              "indexFilter": "",
              "namespace": "metric",
              "q": "M::`db2_database`:(LAST(`row_reads_total`)) BY `db2_server`",
              "queryFuncs": [],
              "type": "simple"
            },
            "type": "sequence",
            "unit": ""
          },
          {
            "color": "",
            "datasource": "dataflux",
            "name": "",
            "qtype": "dql",
            "query": {
              "alias": "",
              "code": "B",
              "dataSource": "db2_database",
              "field": "row_returned_total",
              "fieldFunc": "last",
              "fieldType": "float",
              "fill": null,
              "filters": [],
              "funcList": [],
              "groupBy": [
                "db2_server"
              ],
              "groupByTime": "",
              "indexFilter": "",
              "namespace": "metric",
              "q": "M::`db2_database`:(LAST(`row_returned_total`)) BY `db2_server`",
              "queryFuncs": [],
              "type": "simple"
            },
            "type": "sequence",
            "unit": ""
          },
          {
            "color": "",
            "datasource": "dataflux",
            "name": "",
            "qtype": "dql",
            "query": {
              "alias": "",
              "code": "C",
              "dataSource": "db2_database",
              "field": "row_modified_total",
              "fieldFunc": "last",
              "fieldType": "float",
              "fill": null,
              "filters": [],
              "funcList": [],
              "groupBy": [
                "db2_server"
              ],
              "groupByTime": "",
              "indexFilter": "",
              "namespace": "metric",
              "q": "M::`db2_database`:(LAST(`row_modified_total`)) BY `db2_server`",
              "queryFuncs": [],
              "type": "simple"
            },
            "type": "sequence",
            "unit": ""
          }
        ],
        "type": "sequence"
      },
      {
        "extend": {
          "fixedTime": "",
          "isRefresh": false,
          "settings": {
            "alias": [],
            "chartType": "line",
            "colors": [],
            "compareColors": {
              "dayCompare": "rgba(213,217,226,0.5)",
              "hourCompare": "#D5D9E2",
              "monthCompare": "rgba(213,217,226,0.12)",
              "weekCompare": "rgba(213,217,226,0.25)"
            },
            "compareColorsDark": {
              "dayCompare": "rgba(213,217,226,0.5)",
              "hourCompare": "#D5D9E2",
              "monthCompare": "rgba(213,217,226,0.12)",
              "weekCompare": "rgba(213,217,226,0.25)"
            },
            "compareColorsLight": {
              "dayCompare": "rgba(11,11,12,0.5)",
              "hourCompare": "#0B0B0C",
              "monthCompare": "rgba(11,11,12,0.12)",
              "weekCompare": "rgba(11,11,12,0.3)"
            },
            "compareType": [],
            "currentChartType": "sequence",
            "density": "medium",
            "fixedTime": "",
            "isPercent": false,
            "isTimeInterval": true,
            "legendPostion": "none",
            "legendValues": "",
            "levels": [],
            "mainMeasurementQueryCode": "A",
            "onlyShowGroupName": false,
            "openCompare": false,
            "openStack": false,
            "showFieldMapping": false,
            "showLine": false,
            "showTitle": true,
            "slimit": 20,
            "stackType": "time",
            "timeInterval": "auto",
            "titleDesc": "",
            "units": [],
            "xAxisShowType": "time",
            "yAxixMaxVal": null,
            "yAxixMinVal": null
          }
        },
        "group": {
          "name": "{{.Dashboard.category_database}}"
        },
        "name": "{{.Dashboard.status}}",
        "pos": {
          "h": 11,
          "w": 8,
          "x": 0,
          "y": 0
        },
        "queries": [
          {
            "color": "",
            "datasource": "dataflux",
            "name": "",
            "qtype": "dql",
            "query": {
              "alias": "",
              "code": "A",
              "dataSource": "db2_database",
              "field": "status",
              "fieldFunc": "last",
              "fieldType": "float",
              "fill": null,
              "filters": [],
              "funcList": [],
              "groupBy": [
                "db2_server"
              ],
              "groupByTime": "",
              "indexFilter": "",
              "namespace": "metric",
              "q": "M::`db2_database`:(LAST(`status`)) BY `db2_server`",
              "queryFuncs": [],
              "type": "simple"
            },
            "type": "sequence",
            "unit": ""
          }
        ],
        "type": "sequence"
      },
      {
        "extend": {
          "fixedTime": "",
          "isRefresh": false,
          "settings": {
            "alias": [],
            "chartType": "areaLine",
            "colors": [],
            "compareColors": {
              "dayCompare": "rgba(213,217,226,0.5)",
              "hourCompare": "#D5D9E2",
              "monthCompare": "rgba(213,217,226,0.12)",
              "weekCompare": "rgba(213,217,226,0.25)"
            },
            "compareColorsDark": {
              "dayCompare": "rgba(213,217,226,0.5)",
              "hourCompare": "#D5D9E2",
              "monthCompare": "rgba(213,217,226,0.12)",
              "weekCompare": "rgba(213,217,226,0.25)"
            },
            "compareColorsLight": {
              "dayCompare": "rgba(11,11,12,0.5)",
              "hourCompare": "#0B0B0C",
              "monthCompare": "rgba(11,11,12,0.12)",
              "weekCompare": "rgba(11,11,12,0.3)"
            },
            "compareType": [],
            "currentChartType": "sequence",
            "density": "medium",
            "fixedTime": "",
            "isPercent": false,
            "isTimeInterval": true,
            "legendPostion": "none",
            "legendValues": "",
            "levels": [],
            "mainMeasurementQueryCode": "A",
            "onlyShowGroupName": false,
            "openCompare": false,
            "openStack": false,
            "showFieldMapping": false,
            "showLine": false,
            "showTitle": true,
            "slimit": 20,
            "stackType": "time",
            "timeInterval": "auto",
            "titleDesc": "",
            "units": [],
            "xAxisShowType": "time",
            "yAxixMaxVal": null,
            "yAxixMinVal": null
          }
        },
        "group": {
          "name": "{{.Dashboard.category_log}}"
        },
        "name": "{{.Dashboard.log_used}}",
        "pos": {
          "h": 10,
          "w": 8,
          "x": 0,
          "y": 0
        },
        "queries": [
          {
            "color": "",
            "datasource": "dataflux",
            "name": "",
            "qtype": "dql",
            "query": {
              "alias": "",
              "code": "A",
              "dataSource": "db2_transaction_log",
              "field": "log_used",
              "fieldFunc": "last",
              "fieldType": "float",
              "fill": null,
              "filters": [],
              "funcList": [],
              "groupBy": [
                "db2_server"
              ],
              "groupByTime": "",
              "indexFilter": "",
              "namespace": "metric",
              "q": "M::`db2_transaction_log`:(LAST(`log_used`)) BY `db2_server`",
              "queryFuncs": [],
              "type": "simple"
            },
            "type": "sequence",
            "unit": ""
          }
        ],
        "type": "sequence"
      },
      {
        "extend": {
          "fixedTime": "",
          "isRefresh": false,
          "settings": {
            "alias": [],
            "chartType": "line",
            "colors": [],
            "compareColors": {
              "dayCompare": "rgba(213,217,226,0.5)",
              "hourCompare": "#D5D9E2",
              "monthCompare": "rgba(213,217,226,0.12)",
              "weekCompare": "rgba(213,217,226,0.25)"
            },
            "compareColorsDark": {
              "dayCompare": "rgba(213,217,226,0.5)",
              "hourCompare": "#D5D9E2",
              "monthCompare": "rgba(213,217,226,0.12)",
              "weekCompare": "rgba(213,217,226,0.25)"
            },
            "compareColorsLight": {
              "dayCompare": "rgba(11,11,12,0.5)",
              "hourCompare": "#0B0B0C",
              "monthCompare": "rgba(11,11,12,0.12)",
              "weekCompare": "rgba(11,11,12,0.3)"
            },
            "compareType": [],
            "currentChartType": "sequence",
            "density": "medium",
            "fixedTime": "",
            "isPercent": false,
            "isTimeInterval": true,
            "legendPostion": "none",
            "legendValues": "",
            "levels": [],
            "mainMeasurementQueryCode": "A",
            "onlyShowGroupName": false,
            "openCompare": false,
            "openStack": false,
            "showFieldMapping": false,
            "showLine": false,
            "showTitle": true,
            "slimit": 20,
            "stackType": "time",
            "timeInterval": "auto",
            "titleDesc": "",
            "units": [],
            "xAxisShowType": "time",
            "yAxixMaxVal": null,
            "yAxixMinVal": null
          }
        },
        "group": {
          "name": "{{.Dashboard.category_log}}"
        },
        "name": "{{.Dashboard.log_reads_writes}}",
        "pos": {
          "h": 10,
          "w": 8,
          "x": 8,
          "y": 0
        },
        "queries": [
          {
            "color": "",
            "datasource": "dataflux",
            "name": "",
            "qtype": "dql",
            "query": {
              "alias": "",
              "code": "A",
              "dataSource": "db2_transaction_log",
              "field": "log_reads",
              "fieldFunc": "last",
              "fieldType": "float",
              "fill": null,
              "filters": [],
              "funcList": [],
              "groupBy": [
                "db2_server"
              ],
              "groupByTime": "",
              "indexFilter": "",
              "namespace": "metric",
              "q": "M::`db2_transaction_log`:(LAST(`log_reads`)) BY `db2_server`",
              "queryFuncs": [],
              "type": "simple"
            },
            "type": "sequence",
            "unit": ""
          },
          {
            "color": "",
            "datasource": "dataflux",
            "name": "",
            "qtype": "dql",
            "query": {
              "alias": "",
              "code": "B",
              "dataSource": "db2_transaction_log",
              "field": "log_writes",
              "fieldFunc": "last",
              "fieldType": "float",
              "fill": null,
              "filters": [],
              "funcList": [],
              "groupBy": [
                "db2_server"
              ],
              "groupByTime": "",
              "indexFilter": "",
              "namespace": "metric",
              "q": "M::`db2_transaction_log`:(LAST(`log_writes`)) BY `db2_server`",
              "queryFuncs": [],
              "type": "simple"
            },
            "type": "sequence",
            "unit": ""
          }
        ],
        "type": "sequence"
      },
      {
        "extend": {
          "fixedTime": "",
          "isRefresh": false,
          "settings": {
            "alias": [],
            "chartType": "line",
            "colors": [],
            "compareColors": {
              "dayCompare": "rgba(213,217,226,0.5)",
              "hourCompare": "#D5D9E2",
              "monthCompare": "rgba(213,217,226,0.12)",
              "weekCompare": "rgba(213,217,226,0.25)"
            },
            "compareColorsDark": {
              "dayCompare": "rgba(213,217,226,0.5)",
              "hourCompare": "#D5D9E2",
              "monthCompare": "rgba(213,217,226,0.12)",
              "weekCompare": "rgba(213,217,226,0.25)"
            },
            "compareColorsLight": {
              "dayCompare": "rgba(11,11,12,0.5)",
              "hourCompare": "#0B0B0C",
              "monthCompare": "rgba(11,11,12,0.12)",
              "weekCompare": "rgba(11,11,12,0.3)"
            },
            "compareType": [],
            "currentChartType": "sequence",
            "density": "medium",
            "fixedTime": "",
            "isPercent": false,
            "isTimeInterval": true,
            "legendPostion": "none",
            "legendValues": "",
            "levels": [],
            "mainMeasurementQueryCode": "A",
            "onlyShowGroupName": false,
            "openCompare": false,
            "openStack": false,
            "showFieldMapping": false,
            "showLine": false,
            "showTitle": true,
            "slimit": 20,
            "stackType": "time",
            "timeInterval": "auto",
            "titleDesc": "",
            "units": [
              {
                "key": "last(log_utilized)",
                "name": "last(log_utilized)",
                "unit": "",
                "units": [
                  "percent",
                  "percent"
                ]
              }
            ],
            "xAxisShowType": "time",
            "yAxixMaxVal": null,
            "yAxixMinVal": null
          }
        },
        "group": {
          "name": "{{.Dashboard.category_log}}"
        },
        "name": "{{.Dashboard.log_utilized}}",
        "pos": {
          "h": 10,
          "w": 8,
          "x": 16,
          "y": 0
        },
        "queries": [
          {
            "color": "",
            "datasource": "dataflux",
            "name": "",
            "qtype": "dql",
            "query": {
              "alias": "",
              "code": "A",
              "dataSource": "db2_transaction_log",
              "field": "log_utilized",
              "fieldFunc": "last",
              "fieldType": "float",
              "fill": null,
              "filters": [],
              "funcList": [],
              "groupBy": [
                "db2_server"
              ],
              "groupByTime": "",
              "indexFilter": "",
              "namespace": "metric",
              "q": "M::`db2_transaction_log`:(LAST(`log_utilized`)) BY `db2_server`",
              "queryFuncs": [],
              "type": "simple"
            },
            "type": "sequence",
            "unit": ""
          }
        ],
        "type": "sequence"
      },
      {
        "extend": {
          "fixedTime": "",
          "isRefresh": false,
          "settings": {
            "alias": [],
            "chartType": "line",
            "colors": [],
            "compareColors": {
              "dayCompare": "rgba(213,217,226,0.5)",
              "hourCompare": "#D5D9E2",
              "monthCompare": "rgba(213,217,226,0.12)",
              "weekCompare": "rgba(213,217,226,0.25)"
            },
            "compareColorsDark": {
              "dayCompare": "rgba(213,217,226,0.5)",
              "hourCompare": "#D5D9E2",
              "monthCompare": "rgba(213,217,226,0.12)",
              "weekCompare": "rgba(213,217,226,0.25)"
            },
            "compareColorsLight": {
              "dayCompare": "rgba(11,11,12,0.5)",
              "hourCompare": "#0B0B0C",
              "monthCompare": "rgba(11,11,12,0.12)",
              "weekCompare": "rgba(11,11,12,0.3)"
            },
            "compareType": [],
            "currentChartType": "sequence",
            "density": "medium",
            "fixedTime": "",
            "isPercent": false,
            "isTimeInterval": true,
            "legendPostion": "none",
            "legendValues": "",
            "levels": [],
            "mainMeasurementQueryCode": "A",
            "onlyShowGroupName": false,
            "openCompare": false,
            "openStack": false,
            "showFieldMapping": false,
            "showLine": false,
            "showTitle": true,
            "slimit": 20,
            "stackType": "time",
            "timeInterval": "auto",
            "titleDesc": "",
            "units": [],
            "xAxisShowType": "time",
            "yAxixMaxVal": null,
            "yAxixMinVal": null
          }
        },
        "group": {
          "name": "{{.Dashboard.category_connections}}"
        },
        "name": "{{.Dashboard.connection_max}}",
        "pos": {
          "h": 10,
          "w": 6,
          "x": 12,
          "y": 0
        },
        "queries": [
          {
            "color": "",
            "datasource": "dataflux",
            "name": "",
            "qtype": "dql",
            "query": {
              "alias": "",
              "code": "A",
              "dataSource": "db2_database",
              "field": "connection_max",
              "fieldFunc": "last",
              "fieldType": "float",
              "fill": null,
              "filters": [],
              "funcList": [],
              "groupBy": [
                "db2_server"
              ],
              "groupByTime": "",
              "indexFilter": "",
              "namespace": "metric",
              "q": "M::`db2_database`:(LAST(`connection_max`)) BY `db2_server`",
              "queryFuncs": [],
              "type": "simple"
            },
            "type": "sequence",
            "unit": ""
          }
        ],
        "type": "sequence"
      },
      {
        "extend": {
          "fixedTime": "",
          "isRefresh": false,
          "settings": {
            "alias": [],
            "chartType": "line",
            "colors": [],
            "compareColors": {
              "dayCompare": "rgba(213,217,226,0.5)",
              "hourCompare": "#D5D9E2",
              "monthCompare": "rgba(213,217,226,0.12)",
              "weekCompare": "rgba(213,217,226,0.25)"
            },
            "compareColorsDark": {
              "dayCompare": "rgba(213,217,226,0.5)",
              "hourCompare": "#D5D9E2",
              "monthCompare": "rgba(213,217,226,0.12)",
              "weekCompare": "rgba(213,217,226,0.25)"
            },
            "compareColorsLight": {
              "dayCompare": "rgba(11,11,12,0.5)",
              "hourCompare": "#0B0B0C",
              "monthCompare": "rgba(11,11,12,0.12)",
              "weekCompare": "rgba(11,11,12,0.3)"
            },
            "compareType": [],
            "currentChartType": "sequence",
            "density": "medium",
            "fixedTime": "",
            "isPercent": false,
            "isTimeInterval": true,
            "legendPostion": "none",
            "legendValues": "",
            "levels": [],
            "mainMeasurementQueryCode": "A",
            "onlyShowGroupName": false,
            "openCompare": false,
            "openStack": false,
            "showFieldMapping": false,
            "showLine": false,
            "showTitle": true,
            "slimit": 20,
            "stackType": "time",
            "timeInterval": "auto",
            "titleDesc": "",
            "units": [
              {
                "key": "last(lock_wait)",
                "name": "last(lock_wait)",
                "unit": "",
                "units": [
                  "time",
                  "s"
                ]
              }
            ],
            "xAxisShowType": "time",
            "yAxixMaxVal": null,
            "yAxixMinVal": null
          }
        },
        "group": {
          "name": "{{.Dashboard.category_database}}"
        },
        "name": "{{.Dashboard.lock_wait}}",
        "pos": {
          "h": 11,
          "w": 8,
          "x": 16,
          "y": 0
        },
        "queries": [
          {
            "color": "",
            "datasource": "dataflux",
            "name": "",
            "qtype": "dql",
            "query": {
              "alias": "",
              "code": "A",
              "dataSource": "db2_database",
              "field": "lock_wait",
              "fieldFunc": "last",
              "fieldType": "float",
              "fill": null,
              "filters": [],
              "funcList": [],
              "groupBy": [
                "db2_server"
              ],
              "groupByTime": "",
              "indexFilter": "",
              "namespace": "metric",
              "q": "M::`db2_database`:(LAST(`lock_wait`)) BY `db2_server`",
              "queryFuncs": [],
              "type": "simple"
            },
            "type": "sequence",
            "unit": ""
          }
        ],
        "type": "sequence"
      },
      {
        "extend": {
          "fixedTime": "",
          "isRefresh": false,
          "settings": {
            "alias": [],
            "chartType": "line",
            "colors": [],
            "compareColors": {
              "dayCompare": "rgba(213,217,226,0.5)",
              "hourCompare": "#D5D9E2",
              "monthCompare": "rgba(213,217,226,0.12)",
              "weekCompare": "rgba(213,217,226,0.25)"
            },
            "compareColorsDark": {
              "dayCompare": "rgba(213,217,226,0.5)",
              "hourCompare": "#D5D9E2",
              "monthCompare": "rgba(213,217,226,0.12)",
              "weekCompare": "rgba(213,217,226,0.25)"
            },
            "compareColorsLight": {
              "dayCompare": "rgba(11,11,12,0.5)",
              "hourCompare": "#0B0B0C",
              "monthCompare": "rgba(11,11,12,0.12)",
              "weekCompare": "rgba(11,11,12,0.3)"
            },
            "compareType": [],
            "currentChartType": "sequence",
            "density": "medium",
            "fixedTime": "",
            "isPercent": false,
            "isTimeInterval": true,
            "legendPostion": "none",
            "legendValues": "",
            "levels": [],
            "mainMeasurementQueryCode": "A",
            "onlyShowGroupName": false,
            "openCompare": false,
            "openStack": false,
            "showFieldMapping": false,
            "showLine": false,
            "showTitle": true,
            "slimit": 20,
            "stackType": "time",
            "timeInterval": "auto",
            "titleDesc": "",
            "units": [],
            "xAxisShowType": "time",
            "yAxixMaxVal": null,
            "yAxixMinVal": null
          }
        },
        "group": {
          "name": "{{.Dashboard.category_locks}}"
        },
        "name": "{{.Dashboard.lock_timeouts}}",
        "pos": {
          "h": 10,
          "w": 12,
          "x": 12,
          "y": 0
        },
        "queries": [
          {
            "color": "",
            "datasource": "dataflux",
            "name": "",
            "qtype": "dql",
            "query": {
              "alias": "",
              "code": "A",
              "dataSource": "db2_database",
              "field": "lock_timeouts",
              "fieldFunc": "last",
              "fieldType": "float",
              "fill": null,
              "filters": [],
              "funcList": [],
              "groupBy": [
                "db2_server"
              ],
              "groupByTime": "",
              "indexFilter": "",
              "namespace": "metric",
              "q": "M::`db2_database`:(LAST(`lock_timeouts`)) BY `db2_server`",
              "queryFuncs": [],
              "type": "simple"
            },
            "type": "sequence",
            "unit": ""
          }
        ],
        "type": "sequence"
      },
      {
        "extend": {
          "fixedTime": "",
          "isRefresh": false,
          "settings": {
            "alias": [],
            "chartType": "line",
            "colors": [],
            "compareColors": {
              "dayCompare": "rgba(213,217,226,0.5)",
              "hourCompare": "#D5D9E2",
              "monthCompare": "rgba(213,217,226,0.12)",
              "weekCompare": "rgba(213,217,226,0.25)"
            },
            "compareColorsDark": {
              "dayCompare": "rgba(213,217,226,0.5)",
              "hourCompare": "#D5D9E2",
              "monthCompare": "rgba(213,217,226,0.12)",
              "weekCompare": "rgba(213,217,226,0.25)"
            },
            "compareColorsLight": {
              "dayCompare": "rgba(11,11,12,0.5)",
              "hourCompare": "#0B0B0C",
              "monthCompare": "rgba(11,11,12,0.12)",
              "weekCompare": "rgba(11,11,12,0.3)"
            },
            "compareType": [],
            "currentChartType": "sequence",
            "density": "medium",
            "fixedTime": "",
            "isPercent": false,
            "isTimeInterval": true,
            "legendPostion": "none",
            "legendValues": "",
            "levels": [],
            "mainMeasurementQueryCode": "A",
            "onlyShowGroupName": false,
            "openCompare": false,
            "openStack": false,
            "showFieldMapping": false,
            "showLine": false,
            "showTitle": true,
            "slimit": 20,
            "stackType": "time",
            "timeInterval": "auto",
            "titleDesc": "",
            "units": [],
            "xAxisShowType": "time",
            "yAxixMaxVal": null,
            "yAxixMinVal": null
          }
        },
        "group": {
          "name": "{{.Dashboard.category_bufferpool}}"
        },
        "name": "{{.Dashboard.bufferpool_reads_total}}",
        "pos": {
          "h": 10,
          "w": 12,
          "x": 0,
          "y": 0
        },
        "queries": [
          {
            "color": "",
            "datasource": "dataflux",
            "name": "",
            "qtype": "dql",
            "query": {
              "alias": "",
              "code": "A",
              "dataSource": "db2_buffer_pool",
              "field": "bufferpool_reads_total",
              "fieldFunc": "last",
              "fieldType": "float",
              "fill": null,
              "filters": [],
              "funcList": [],
              "groupBy": [
                "db2_server"
              ],
              "groupByTime": "",
              "indexFilter": "",
              "namespace": "metric",
              "q": "M::`db2_buffer_pool`:(LAST(`bufferpool_reads_total`)) BY `db2_server`",
              "queryFuncs": [],
              "type": "simple"
            },
            "type": "sequence",
            "unit": ""
          }
        ],
        "type": "sequence"
      },
      {
        "extend": {
          "fixedTime": "",
          "isRefresh": false,
          "settings": {
            "alias": [],
            "chartType": "line",
            "colors": [],
            "compareColors": {
              "dayCompare": "rgba(213,217,226,0.5)",
              "hourCompare": "#D5D9E2",
              "monthCompare": "rgba(213,217,226,0.12)",
              "weekCompare": "rgba(213,217,226,0.25)"
            },
            "compareColorsDark": {
              "dayCompare": "rgba(213,217,226,0.5)",
              "hourCompare": "#D5D9E2",
              "monthCompare": "rgba(213,217,226,0.12)",
              "weekCompare": "rgba(213,217,226,0.25)"
            },
            "compareColorsLight": {
              "dayCompare": "rgba(11,11,12,0.5)",
              "hourCompare": "#0B0B0C",
              "monthCompare": "rgba(11,11,12,0.12)",
              "weekCompare": "rgba(11,11,12,0.3)"
            },
            "compareType": [],
            "currentChartType": "sequence",
            "density": "medium",
            "fixedTime": "",
            "isPercent": false,
            "isTimeInterval": true,
            "legendPostion": "none",
            "legendValues": "",
            "levels": [],
            "mainMeasurementQueryCode": "A",
            "onlyShowGroupName": false,
            "openCompare": false,
            "openStack": false,
            "showFieldMapping": false,
            "showLine": false,
            "showTitle": true,
            "slimit": 20,
            "stackType": "time",
            "timeInterval": "auto",
            "titleDesc": "",
            "units": [
              {
                "key": "last(bufferpool_hit_percent)",
                "name": "last(bufferpool_hit_percent)",
                "unit": "",
                "units": [
                  "percent",
                  "percent"
                ]
              }
            ],
            "xAxisShowType": "time",
            "yAxixMaxVal": null,
            "yAxixMinVal": null
          }
        },
        "group": {
          "name": "{{.Dashboard.category_bufferpool}}"
        },
        "name": "{{.Dashboard.bufferpool_hit_percent}}",
        "pos": {
          "h": 10,
          "w": 12,
          "x": 12,
          "y": 0
        },
        "queries": [
          {
            "color": "",
            "datasource": "dataflux",
            "name": "",
            "qtype": "dql",
            "query": {
              "alias": "",
              "code": "A",
              "dataSource": "db2_buffer_pool",
              "field": "bufferpool_hit_percent",
              "fieldFunc": "last",
              "fieldType": "float",
              "fill": null,
              "filters": [],
              "funcList": [],
              "groupBy": [
                "db2_server"
              ],
              "groupByTime": "",
              "indexFilter": "",
              "namespace": "metric",
              "q": "M::`db2_buffer_pool`:(LAST(`bufferpool_hit_percent`)) BY `db2_server`",
              "queryFuncs": [],
              "type": "simple"
            },
            "type": "sequence",
            "unit": ""
          }
        ],
        "type": "sequence"
      },
      {
        "extend": {
          "fixedTime": "",
          "isRefresh": false,
          "settings": {
            "alias": [],
            "bar": {
              "direction": "horizontal",
              "xAxisShowType": "groupBy"
            },
            "chartType": "bar",
            "color": "#498bfe",
            "colors": [],
            "currentChartType": "toplist",
            "fixedTime": "",
            "isTimeInterval": false,
            "levels": [],
            "openCompare": false,
            "showFieldMapping": false,
            "showTableHead": true,
            "showTitle": true,
            "showTopSize": true,
            "table": {
              "queryMode": "toGroupColumn"
            },
            "tableSortMetricName": "",
            "tableSortType": "top",
            "timeInterval": "default",
            "titleDesc": "",
            "topSize": 10,
            "units": [
              {
                "key": "last(tablespace_utilized)",
                "name": "last(tablespace_utilized)",
                "unit": "",
                "units": [
                  "percent",
                  "percent"
                ]
              }
            ]
          }
        },
        "group": {
          "name": "{{.Dashboard.category_tablespace}}"
        },
        "name": "{{.Dashboard.tablespace_utilized}}",
        "pos": {
          "h": 25,
          "w": 12,
          "x": 0,
          "y": 0
        },
        "queries": [
          {
            "color": "",
            "datasource": "dataflux",
            "name": "",
            "qtype": "dql",
            "query": {
              "alias": "",
              "code": "A",
              "dataSource": "db2_table_space",
              "field": "tablespace_utilized",
              "fieldFunc": "last",
              "fieldType": "float",
              "fill": null,
              "filters": [],
              "funcList": [
                null,
                "top:10"
              ],
              "groupBy": [
                "tablespace_name"
              ],
              "groupByTime": "",
              "indexFilter": "",
              "namespace": "metric",
              "q": "M::`db2_table_space`:(LAST(`tablespace_utilized`)) BY `tablespace_name`",
              "queryFuncs": [],
              "type": "simple"
            },
            "type": "toplist",
            "unit": ""
          }
        ],
        "type": "toplist"
      },
      {
        "extend": {
          "fixedTime": "",
          "isRefresh": false,
          "settings": {
            "alias": [],
            "chartType": "areaLine",
            "colors": [],
            "compareColors": {
              "dayCompare": "rgba(213,217,226,0.5)",
              "hourCompare": "#D5D9E2",
              "monthCompare": "rgba(213,217,226,0.12)",
              "weekCompare": "rgba(213,217,226,0.25)"
            },
            "compareColorsDark": {
              "dayCompare": "rgba(213,217,226,0.5)",
              "hourCompare": "#D5D9E2",
              "monthCompare": "rgba(213,217,226,0.12)",
              "weekCompare": "rgba(213,217,226,0.25)"
            },
            "compareColorsLight": {
              "dayCompare": "rgba(11,11,12,0.5)",
              "hourCompare": "#0B0B0C",
              "monthCompare": "rgba(11,11,12,0.12)",
              "weekCompare": "rgba(11,11,12,0.3)"
            },
            "compareType": [],
            "currentChartType": "sequence",
            "density": "medium",
            "fixedTime": "",
            "isPercent": false,
            "isTimeInterval": true,
            "legendPostion": "none",
            "legendValues": "",
            "levels": [],
            "mainMeasurementQueryCode": "A",
            "onlyShowGroupName": false,
            "openCompare": false,
            "openStack": false,
            "showFieldMapping": false,
            "showLine": false,
            "showTitle": true,
            "slimit": 20,
            "stackType": "time",
            "timeInterval": "auto",
            "titleDesc": "",
            "units": [
              {
                "key": "last(tablespace_usable)",
                "name": "last(tablespace_usable)",
                "unit": "",
                "units": [
                  "digital",
                  "b"
                ]
              },
              {
                "key": "last(tablespace_used)",
                "name": "last(tablespace_used)",
                "unit": "",
                "units": [
                  "digital",
                  "b"
                ]
              }
            ],
            "xAxisShowType": "time",
            "yAxixMaxVal": null,
            "yAxixMinVal": null
          }
        },
        "group": {
          "name": "{{.Dashboard.category_tablespace}}"
        },
        "name": "{{.Dashboard.tablespace_usable_used}}",
        "pos": {
          "h": 25,
          "w": 12,
          "x": 12,
          "y": 0
        },
        "queries": [
          {
            "color": "",
            "datasource": "dataflux",
            "name": "",
            "qtype": "dql",
            "query": {
              "alias": "",
              "code": "A",
              "dataSource": "db2_table_space",
              "field": "tablespace_usable",
              "fieldFunc": "last",
              "fieldType": "float",
              "fill": null,
              "filters": [],
              "funcList": [],
              "groupBy": [
                "db2_server"
              ],
              "groupByTime": "",
              "indexFilter": "",
              "namespace": "metric",
              "q": "M::`db2_table_space`:(LAST(`tablespace_usable`)) BY `db2_server`",
              "queryFuncs": [],
              "type": "simple"
            },
            "type": "sequence",
            "unit": ""
          },
          {
            "color": "",
            "datasource": "dataflux",
            "name": "",
            "qtype": "dql",
            "query": {
              "alias": "",
              "code": "B",
              "dataSource": "db2_table_space",
              "field": "tablespace_used",
              "fieldFunc": "last",
              "fieldType": "float",
              "fill": null,
              "filters": [],
              "funcList": [],
              "groupBy": [
                "db2_server"
              ],
              "groupByTime": "",
              "indexFilter": "",
              "namespace": "metric",
              "q": "M::`db2_table_space`:(LAST(`tablespace_used`)) BY `db2_server`",
              "queryFuncs": [],
              "type": "simple"
            },
            "type": "sequence",
            "unit": ""
          }
        ],
        "type": "sequence"
      },
      {
        "extend": {
          "fixedTime": "",
          "isRefresh": false,
          "settings": {
            "alias": [],
            "chartType": "line",
            "colors": [],
            "compareColors": {
              "dayCompare": "rgba(213,217,226,0.5)",
              "hourCompare": "#D5D9E2",
              "monthCompare": "rgba(213,217,226,0.12)",
              "weekCompare": "rgba(213,217,226,0.25)"
            },
            "compareColorsDark": {
              "dayCompare": "rgba(213,217,226,0.5)",
              "hourCompare": "#D5D9E2",
              "monthCompare": "rgba(213,217,226,0.12)",
              "weekCompare": "rgba(213,217,226,0.25)"
            },
            "compareColorsLight": {
              "dayCompare": "rgba(11,11,12,0.5)",
              "hourCompare": "#0B0B0C",
              "monthCompare": "rgba(11,11,12,0.12)",
              "weekCompare": "rgba(11,11,12,0.3)"
            },
            "compareType": [],
            "currentChartType": "sequence",
            "density": "medium",
            "fixedTime": "",
            "isPercent": false,
            "isTimeInterval": true,
            "legendPostion": "none",
            "legendValues": "",
            "levels": [],
            "mainMeasurementQueryCode": "A",
            "onlyShowGroupName": false,
            "openCompare": false,
            "openStack": false,
            "showFieldMapping": false,
            "showLine": false,
            "showTitle": true,
            "slimit": 20,
            "stackType": "time",
            "timeInterval": "auto",
            "titleDesc": "",
            "units": [],
            "xAxisShowType": "time",
            "yAxixMaxVal": null,
            "yAxixMinVal": null
          }
        },
        "group": {
          "name": "{{.Dashboard.category_connections}}"
        },
        "name": "{{.Dashboard.application_executing}}",
        "pos": {
          "h": 10,
          "w": 6,
          "x": 18,
          "y": 0
        },
        "queries": [
          {
            "color": "",
            "datasource": "dataflux",
            "name": "",
            "qtype": "dql",
            "query": {
              "alias": "",
              "code": "A",
              "dataSource": "db2_database",
              "field": "application_executing",
              "fieldFunc": "last",
              "fieldType": "float",
              "fill": null,
              "filters": [],
              "funcList": [],
              "groupBy": [
                "db2_server"
              ],
              "groupByTime": "",
              "indexFilter": "",
              "namespace": "metric",
              "q": "M::`db2_database`:(LAST(`application_executing`)) BY `db2_server`",
              "queryFuncs": [],
              "type": "simple"
            },
            "type": "sequence",
            "unit": ""
          }
        ],
        "type": "sequence"
      },
      {
        "extend": {
          "fixedTime": "",
          "isRefresh": false,
          "settings": {
            "alias": [],
            "chartType": "line",
            "colors": [],
            "compareColors": {
              "dayCompare": "rgba(213,217,226,0.5)",
              "hourCompare": "#D5D9E2",
              "monthCompare": "rgba(213,217,226,0.12)",
              "weekCompare": "rgba(213,217,226,0.25)"
            },
            "compareColorsDark": {
              "dayCompare": "rgba(213,217,226,0.5)",
              "hourCompare": "#D5D9E2",
              "monthCompare": "rgba(213,217,226,0.12)",
              "weekCompare": "rgba(213,217,226,0.25)"
            },
            "compareColorsLight": {
              "dayCompare": "rgba(11,11,12,0.5)",
              "hourCompare": "#0B0B0C",
              "monthCompare": "rgba(11,11,12,0.12)",
              "weekCompare": "rgba(11,11,12,0.3)"
            },
            "compareType": [],
            "currentChartType": "sequence",
            "density": "medium",
            "fixedTime": "",
            "isPercent": false,
            "isTimeInterval": true,
            "legendPostion": "none",
            "legendValues": "",
            "levels": [],
            "mainMeasurementQueryCode": "A",
            "onlyShowGroupName": false,
            "openCompare": false,
            "openStack": false,
            "showFieldMapping": false,
            "showLine": false,
            "showTitle": true,
            "slimit": 20,
            "stackType": "time",
            "timeInterval": "auto",
            "titleDesc": "",
            "units": [],
            "xAxisShowType": "time",
            "yAxixMaxVal": null,
            "yAxixMinVal": null
          }
        },
        "group": {
          "name": "{{.Dashboard.category_readwrite}}"
        },
        "name": "{{.Dashboard.bufferpool_column_reads_total}}",
        "pos": {
          "h": 12,
          "w": 8,
          "x": 8,
          "y": 0
        },
        "queries": [
          {
            "color": "",
            "datasource": "dataflux",
            "name": "",
            "qtype": "dql",
            "query": {
              "alias": "",
              "code": "A",
              "dataSource": "db2_buffer_pool",
              "field": "bufferpool_column_reads_total",
              "fieldFunc": "last",
              "fieldType": "float",
              "fill": null,
              "filters": [],
              "funcList": [],
              "groupBy": [
                "db2_server"
              ],
              "groupByTime": "",
              "indexFilter": "",
              "namespace": "metric",
              "q": "M::`db2_buffer_pool`:(LAST(`bufferpool_column_reads_total`)) BY `db2_server`",
              "queryFuncs": [],
              "type": "simple"
            },
            "type": "sequence",
            "unit": ""
          }
        ],
        "type": "sequence"
      },
      {
        "extend": {
          "fixedTime": "",
          "isRefresh": false,
          "settings": {
            "alias": [],
            "chartType": "line",
            "colors": [],
            "compareColors": {
              "dayCompare": "rgba(213,217,226,0.5)",
              "hourCompare": "#D5D9E2",
              "monthCompare": "rgba(213,217,226,0.12)",
              "weekCompare": "rgba(213,217,226,0.25)"
            },
            "compareColorsDark": {
              "dayCompare": "rgba(213,217,226,0.5)",
              "hourCompare": "#D5D9E2",
              "monthCompare": "rgba(213,217,226,0.12)",
              "weekCompare": "rgba(213,217,226,0.25)"
            },
            "compareColorsLight": {
              "dayCompare": "rgba(11,11,12,0.5)",
              "hourCompare": "#0B0B0C",
              "monthCompare": "rgba(11,11,12,0.12)",
              "weekCompare": "rgba(11,11,12,0.3)"
            },
            "compareType": [],
            "currentChartType": "sequence",
            "density": "medium",
            "fixedTime": "",
            "isPercent": false,
            "isTimeInterval": true,
            "legendPostion": "none",
            "legendValues": "",
            "levels": [],
            "mainMeasurementQueryCode": "A",
            "onlyShowGroupName": false,
            "openCompare": false,
            "openStack": false,
            "showFieldMapping": false,
            "showLine": false,
            "showTitle": true,
            "slimit": 20,
            "stackType": "time",
            "timeInterval": "auto",
            "titleDesc": "",
            "units": [],
            "xAxisShowType": "time",
            "yAxixMaxVal": null,
            "yAxixMinVal": null
          }
        },
        "group": {
          "name": "{{.Dashboard.category_readwrite}}"
        },
        "name": "{{.Dashboard.bufferpool_index_reads_total}}",
        "pos": {
          "h": 12,
          "w": 8,
          "x": 16,
          "y": 0
        },
        "queries": [
          {
            "color": "",
            "datasource": "dataflux",
            "name": "",
            "qtype": "dql",
            "query": {
              "alias": "",
              "code": "A",
              "dataSource": "db2_buffer_pool",
              "field": "bufferpool_index_reads_total",
              "fieldFunc": "last",
              "fieldType": "float",
              "fill": null,
              "filters": [],
              "funcList": [],
              "groupBy": [
                "db2_server"
              ],
              "groupByTime": "",
              "indexFilter": "",
              "namespace": "metric",
              "q": "M::`db2_buffer_pool`:(LAST(`bufferpool_index_reads_total`)) BY `db2_server`",
              "queryFuncs": [],
              "type": "simple"
            },
            "type": "sequence",
            "unit": ""
          }
        ],
        "type": "sequence"
      },
      {
        "extend": {
          "fixedTime": "",
          "isRefresh": false,
          "settings": {
            "alias": [],
            "chartType": "line",
            "colors": [],
            "compareColors": {
              "dayCompare": "rgba(213,217,226,0.5)",
              "hourCompare": "#D5D9E2",
              "monthCompare": "rgba(213,217,226,0.12)",
              "weekCompare": "rgba(213,217,226,0.25)"
            },
            "compareColorsDark": {
              "dayCompare": "rgba(213,217,226,0.5)",
              "hourCompare": "#D5D9E2",
              "monthCompare": "rgba(213,217,226,0.12)",
              "weekCompare": "rgba(213,217,226,0.25)"
            },
            "compareColorsLight": {
              "dayCompare": "rgba(11,11,12,0.5)",
              "hourCompare": "#0B0B0C",
              "monthCompare": "rgba(11,11,12,0.12)",
              "weekCompare": "rgba(11,11,12,0.3)"
            },
            "compareType": [],
            "currentChartType": "sequence",
            "density": "medium",
            "fixedTime": "",
            "isPercent": false,
            "isTimeInterval": true,
            "legendPostion": "none",
            "legendValues": "",
            "levels": [],
            "mainMeasurementQueryCode": "A",
            "onlyShowGroupName": false,
            "openCompare": false,
            "openStack": false,
            "showFieldMapping": false,
            "showLine": false,
            "showTitle": true,
            "slimit": 20,
            "stackType": "time",
            "timeInterval": "auto",
            "titleDesc": "",
            "units": [],
            "xAxisShowType": "time",
            "yAxixMaxVal": null,
            "yAxixMinVal": null
          }
        },
        "group": {
          "name": "{{.Dashboard.category_readwrite}}"
        },
        "name": "{{.Dashboard.bufferpool_xda_reads_total}}",
        "pos": {
          "h": 10,
          "w": 12,
          "x": 0,
          "y": 12
        },
        "queries": [
          {
            "color": "",
            "datasource": "dataflux",
            "name": "",
            "qtype": "dql",
            "query": {
              "alias": "",
              "code": "A",
              "dataSource": "db2_buffer_pool",
              "field": "bufferpool_xda_reads_total",
              "fieldFunc": "last",
              "fieldType": "float",
              "fill": null,
              "filters": [],
              "funcList": [],
              "groupBy": [
                "db2_server"
              ],
              "groupByTime": "",
              "indexFilter": "",
              "namespace": "metric",
              "q": "M::`db2_buffer_pool`:(LAST(`bufferpool_xda_reads_total`)) BY `db2_server`",
              "queryFuncs": [],
              "type": "simple"
            },
            "type": "sequence",
            "unit": ""
          }
        ],
        "type": "sequence"
      },
      {
        "extend": {
          "fixedTime": "",
          "isRefresh": false,
          "settings": {
            "alias": [],
            "chartType": "line",
            "colors": [],
            "compareColors": {
              "dayCompare": "rgba(213,217,226,0.5)",
              "hourCompare": "#D5D9E2",
              "monthCompare": "rgba(213,217,226,0.12)",
              "weekCompare": "rgba(213,217,226,0.25)"
            },
            "compareColorsDark": {
              "dayCompare": "rgba(213,217,226,0.5)",
              "hourCompare": "#D5D9E2",
              "monthCompare": "rgba(213,217,226,0.12)",
              "weekCompare": "rgba(213,217,226,0.25)"
            },
            "compareColorsLight": {
              "dayCompare": "rgba(11,11,12,0.5)",
              "hourCompare": "#0B0B0C",
              "monthCompare": "rgba(11,11,12,0.12)",
              "weekCompare": "rgba(11,11,12,0.3)"
            },
            "compareType": [],
            "currentChartType": "sequence",
            "density": "medium",
            "fixedTime": "",
            "isPercent": false,
            "isTimeInterval": true,
            "legendPostion": "none",
            "legendValues": "",
            "levels": [],
            "mainMeasurementQueryCode": "A",
            "onlyShowGroupName": false,
            "openCompare": false,
            "openStack": false,
            "showFieldMapping": false,
            "showLine": false,
            "showTitle": true,
            "slimit": 20,
            "stackType": "time",
            "timeInterval": "auto",
            "titleDesc": "",
            "units": [],
            "xAxisShowType": "time",
            "yAxixMaxVal": null,
            "yAxixMinVal": null
          }
        },
        "group": {
          "name": "{{.Dashboard.category_readwrite}}"
        },
        "name": "{{.Dashboard.bufferpool_data_reads_total}}",
        "pos": {
          "h": 10,
          "w": 12,
          "x": 12,
          "y": 12
        },
        "queries": [
          {
            "color": "",
            "datasource": "dataflux",
            "name": "",
            "qtype": "dql",
            "query": {
              "alias": "",
              "code": "A",
              "dataSource": "db2_buffer_pool",
              "field": "bufferpool_data_reads_total",
              "fieldFunc": "last",
              "fieldType": "float",
              "fill": null,
              "filters": [],
              "funcList": [],
              "groupBy": [
                "db2_server"
              ],
              "groupByTime": "",
              "indexFilter": "",
              "namespace": "metric",
              "q": "M::`db2_buffer_pool`:(LAST(`bufferpool_data_reads_total`)) BY `db2_server`",
              "queryFuncs": [],
              "type": "simple"
            },
            "type": "sequence",
            "unit": ""
          }
        ],
        "type": "sequence"
      },
      {
        "extend": {
          "fixedTime": "",
          "settings": {
            "addColumns": [
              {
                "field": "df_status",
                "headerName": ""
              },
              {
                "field": "df_title",
                "headerName": ""
              }
            ],
            "alias": [],
            "colors": [],
            "currentChartType": "alarm",
            "fixedTime": "",
            "inColumns": [
              {
                "cellRenderer": "StatusCellRender",
                "field": "time",
                "filterParams": {},
                "headerName": "",
                "showTooltip": false
              }
            ],
            "index": "",
            "isTimeInterval": false,
            "levels": [],
            "showFieldMapping": false,
            "showPart": "all",
            "showTitle": true,
            "timeInterval": "",
            "titleDesc": "",
            "units": []
          }
        },
        "group": {
          "name": "{{.Dashboard.category_overview}}"
        },
        "name": "{{.Dashboard.alarm}}",
        "pos": {
          "h": 17,
          "w": 24,
          "x": 0,
          "y": 0
        },
        "queries": [
          {
            "color": "",
            "datasource": "dataflux",
            "name": "",
            "noTimeRange": false,
            "qtype": "dql",
            "query": {
              "alias": "",
              "code": "A",
              "dataSource": "monitor",
              "disableMultipleField": false,
              "field": null,
              "fieldFunc": "count",
              "fieldType": "",
              "fields": [
                {
                  "alias": "",
                  "field": "df_status"
                },
                {
                  "alias": "",
                  "field": "df_title"
                }
              ],
              "fill": null,
              "filters": [],
              "funcList": [],
              "groupBy": [],
              "groupByTime": "",
              "indexFilter": "",
              "namespace": "event",
              "q": "E::`monitor`:(`df_status` AS ``, `df_title` AS ``)",
              "queryFuncs": [],
              "search": "db2_status_exception",
              "type": "simple"
            },
            "type": "alarm",
            "unit": ""
          }
        ],
        "type": "alarm"
      }
    ],
    "groups": [
      "{{.Dashboard.category_overview}}",
      "{{.Dashboard.category_database}}",
      "{{.Dashboard.category_log}}",
      "{{.Dashboard.category_connections}}",
      "{{.Dashboard.category_bufferpool}}",
      "{{.Dashboard.category_locks}}",
      "{{.Dashboard.category_readwrite}}",
      "{{.Dashboard.category_tablespace}}"
    ],
    "type": "template",
    "vars": []
  },
  "summary": "",
  "tagInfo": [],
  "thumbnail": "",
  "title": "IBM Db2 "
}